<?xml version="1.0" encoding="UTF-8"?>
<tph_report>
  <report id="0">
    <timestamp>
      <date>2019.02.24</date>
      <time>22:06:36.035</time>
    </timestamp>
    <lps331>
      <t>24,5</t>
      <p>1011</p>
    </lps331>
    <hdc1080>
      <t>25,83282</t>
      <hum>35</hum>
    </hdc1080>
  </report>
  <report id="1">
    <timestamp>
      <date>2019.02.24</date>
      <time>22:06:36.625</time>
    </timestamp>
    <lps331>
      <t>24,5</t>
      <p>1011</p>
    </lps331>
    <hdc1080>
      <t>25,82275</t>
      <hum>35</hum>
    </hdc1080>
  </report>
  <report id="2">
    <timestamp>
      <date>2019.02.24</date>
      <time>22:06:37.714</time>
    </timestamp>
    <lps331>
      <t>24,5</t>
      <p>1011</p>
    </lps331>
    <hdc1080>
      <t>25,83282</t>
      <hum>35</hum>
    </hdc1080>
  </report>
  <report id="3">
    <timestamp>
      <date>2019.02.24</date>
      <time>22:06:38.808</time>
    </timestamp>
    <lps331>
      <t>24,5</t>
      <p>1011</p>
    </lps331>
    <hdc1080>
      <t>25,83282</t>
      <hum>36</hum>
    </hdc1080>
  </report>
  <report id="4">
    <timestamp>
      <date>2019.02.24</date>
      <time>22:06:39.902</time>
    </timestamp>
    <lps331>
      <t>24,5</t>
      <p>1011</p>
    </lps331>
    <hdc1080>
      <t>25,83282</t>
      <hum>36</hum>
    </hdc1080>
  </report>
  <report id="5">
    <timestamp>
      <date>2019.02.24</date>
      <time>22:06:40.996</time>
    </timestamp>
    <lps331>
      <t>24,5</t>
      <p>1011</p>
    </lps331>
    <hdc1080>
      <t>25,83282</t>
      <hum>36</hum>
    </hdc1080>
  </report>
  <report id="6">
    <timestamp>
      <date>2019.02.24</date>
      <time>22:06:42.597</time>
    </timestamp>
    <lps331>
      <t>24,5</t>
      <p>1011</p>
    </lps331>
    <hdc1080>
      <t>25,87311</t>
      <hum>35</hum>
    </hdc1080>
  </report>
  <report id="7">
    <timestamp>
      <date>2019.02.24</date>
      <time>22:06:43.691</time>
    </timestamp>
    <lps331>
      <t>24,5</t>
      <p>1011</p>
    </lps331>
    <hdc1080>
      <t>25,83282</t>
      <hum>35</hum>
    </hdc1080>
  </report>
  <report id="8">
    <timestamp>
      <date>2019.02.24</date>
      <time>22:06:44.785</time>
    </timestamp>
    <lps331>
      <t>24,5</t>
      <p>1011</p>
    </lps331>
    <hdc1080>
      <t>25,85297</t>
      <hum>35</hum>
    </hdc1080>
  </report>
  <report id="9">
    <timestamp>
      <date>2019.02.24</date>
      <time>22:06:45.875</time>
    </timestamp>
    <lps331>
      <t>24,5</t>
      <p>1011</p>
    </lps331>
    <hdc1080>
      <t>25,85297</t>
      <hum>35</hum>
    </hdc1080>
  </report>
  <report id="10">
    <timestamp>
      <date>2019.02.24</date>
      <time>22:06:46.968</time>
    </timestamp>
    <lps331>
      <t>24,5</t>
      <p>1011</p>
    </lps331>
    <hdc1080>
      <t>25,83282</t>
      <hum>35</hum>
    </hdc1080>
  </report>
  <report id="11">
    <timestamp>
      <date>2019.02.24</date>
      <time>22:06:48.062</time>
    </timestamp>
    <lps331>
      <t>24,5</t>
      <p>1011</p>
    </lps331>
    <hdc1080>
      <t>25,85297</t>
      <hum>34</hum>
    </hdc1080>
  </report>
  <report id="12">
    <timestamp>
      <date>2019.02.24</date>
      <time>22:06:48.652</time>
    </timestamp>
    <lps331>
      <t>24,5</t>
      <p>1011</p>
    </lps331>
    <hdc1080>
      <t>25,83282</t>
      <hum>34</hum>
    </hdc1080>
  </report>
  <report id="13">
    <timestamp>
      <date>2019.02.24</date>
      <time>22:06:49.746</time>
    </timestamp>
    <lps331>
      <t>24,5</t>
      <p>1011</p>
    </lps331>
    <hdc1080>
      <t>25,85297</t>
      <hum>34</hum>
    </hdc1080>
  </report>
  <report id="14">
    <timestamp>
      <date>2019.02.24</date>
      <time>22:06:50.835</time>
    </timestamp>
    <lps331>
      <t>24,5</t>
      <p>1011</p>
    </lps331>
    <hdc1080>
      <t>25,85297</t>
      <hum>34</hum>
    </hdc1080>
  </report>
  <report id="15">
    <timestamp>
      <date>2019.02.24</date>
      <time>22:06:51.929</time>
    </timestamp>
    <lps331>
      <t>24,5</t>
      <p>1011</p>
    </lps331>
    <hdc1080>
      <t>25,85297</t>
      <hum>34</hum>
    </hdc1080>
  </report>
  <report id="16">
    <timestamp>
      <date>2019.02.24</date>
      <time>22:06:53.023</time>
    </timestamp>
    <lps331>
      <t>24,5</t>
      <p>1011</p>
    </lps331>
    <hdc1080>
      <t>25,85297</t>
      <hum>34</hum>
    </hdc1080>
  </report>
  <report id="17">
    <timestamp>
      <date>2019.02.24</date>
      <time>22:06:53.613</time>
    </timestamp>
    <lps331>
      <t>24,5</t>
      <p>1011</p>
    </lps331>
    <hdc1080>
      <t>25,83282</t>
      <hum>34</hum>
    </hdc1080>
  </report>
  <report id="18">
    <timestamp>
      <date>2019.02.24</date>
      <time>22:06:54.707</time>
    </timestamp>
    <lps331>
      <t>24,5</t>
      <p>1011</p>
    </lps331>
    <hdc1080>
      <t>25,87311</t>
      <hum>34</hum>
    </hdc1080>
  </report>
  <report id="19">
    <timestamp>
      <date>2019.02.24</date>
      <time>22:06:55.796</time>
    </timestamp>
    <lps331>
      <t>24,5</t>
      <p>1011</p>
    </lps331>
    <hdc1080>
      <t>25,83282</t>
      <hum>34</hum>
    </hdc1080>
  </report>
  <report id="20">
    <timestamp>
      <date>2019.02.24</date>
      <time>22:06:56.890</time>
    </timestamp>
    <lps331>
      <t>24,5</t>
      <p>1011</p>
    </lps331>
    <hdc1080>
      <t>25,83282</t>
      <hum>34</hum>
    </hdc1080>
  </report>
  <report id="21">
    <timestamp>
      <date>2019.02.24</date>
      <time>22:06:57.984</time>
    </timestamp>
    <lps331>
      <t>24,5</t>
      <p>1011</p>
    </lps331>
    <hdc1080>
      <t>25,85297</t>
      <hum>34</hum>
    </hdc1080>
  </report>
  <report id="22">
    <timestamp>
      <date>2019.02.24</date>
      <time>22:06:59.078</time>
    </timestamp>
    <lps331>
      <t>24,5</t>
      <p>1011</p>
    </lps331>
    <hdc1080>
      <t>25,85297</t>
      <hum>34</hum>
    </hdc1080>
  </report>
  <report id="23">
    <timestamp>
      <date>2019.02.24</date>
      <time>22:06:59.667</time>
    </timestamp>
    <lps331>
      <t>24,5</t>
      <p>1011</p>
    </lps331>
    <hdc1080>
      <t>25,83282</t>
      <hum>34</hum>
    </hdc1080>
  </report>
  <report id="24">
    <timestamp>
      <date>2019.02.24</date>
      <time>22:07:00.761</time>
    </timestamp>
    <lps331>
      <t>24,5</t>
      <p>1010</p>
    </lps331>
    <hdc1080>
      <t>25,83282</t>
      <hum>34</hum>
    </hdc1080>
  </report>
  <report id="25">
    <timestamp>
      <date>2019.02.24</date>
      <time>22:07:01.855</time>
    </timestamp>
    <lps331>
      <t>24,5</t>
      <p>1011</p>
    </lps331>
    <hdc1080>
      <t>25,85297</t>
      <hum>34</hum>
    </hdc1080>
  </report>
  <report id="26">
    <timestamp>
      <date>2019.02.24</date>
      <time>22:07:02.949</time>
    </timestamp>
    <lps331>
      <t>24,5</t>
      <p>1011</p>
    </lps331>
    <hdc1080>
      <t>25,85297</t>
      <hum>34</hum>
    </hdc1080>
  </report>
  <report id="27">
    <timestamp>
      <date>2019.02.24</date>
      <time>22:07:04.039</time>
    </timestamp>
    <lps331>
      <t>24,5</t>
      <p>1011</p>
    </lps331>
    <hdc1080>
      <t>25,83282</t>
      <hum>34</hum>
    </hdc1080>
  </report>
  <report id="28">
    <timestamp>
      <date>2019.02.24</date>
      <time>22:07:04.628</time>
    </timestamp>
    <lps331>
      <t>24,5</t>
      <p>1010</p>
    </lps331>
    <hdc1080>
      <t>25,85297</t>
      <hum>34</hum>
    </hdc1080>
  </report>
  <report id="29">
    <timestamp>
      <date>2019.02.24</date>
      <time>22:07:05.722</time>
    </timestamp>
    <lps331>
      <t>24,5</t>
      <p>1011</p>
    </lps331>
    <hdc1080>
      <t>25,85297</t>
      <hum>34</hum>
    </hdc1080>
  </report>
  <report id="30">
    <timestamp>
      <date>2019.02.24</date>
      <time>22:07:06.812</time>
    </timestamp>
    <lps331>
      <t>24,5</t>
      <p>1011</p>
    </lps331>
    <hdc1080>
      <t>25,83282</t>
      <hum>34</hum>
    </hdc1080>
  </report>
  <report id="31">
    <timestamp>
      <date>2019.02.24</date>
      <time>22:07:07.906</time>
    </timestamp>
    <lps331>
      <t>24,5</t>
      <p>1011</p>
    </lps331>
    <hdc1080>
      <t>25,85297</t>
      <hum>34</hum>
    </hdc1080>
  </report>
  <report id="32">
    <timestamp>
      <date>2019.02.24</date>
      <time>22:07:09.000</time>
    </timestamp>
    <lps331>
      <t>24,5</t>
      <p>1011</p>
    </lps331>
    <hdc1080>
      <t>25,85297</t>
      <hum>34</hum>
    </hdc1080>
  </report>
  <report id="33">
    <timestamp>
      <date>2019.02.24</date>
      <time>22:07:09.589</time>
    </timestamp>
    <lps331>
      <t>24,5</t>
      <p>1011</p>
    </lps331>
    <hdc1080>
      <t>25,85297</t>
      <hum>34</hum>
    </hdc1080>
  </report>
  <report id="34">
    <timestamp>
      <date>2019.02.24</date>
      <time>22:07:10.679</time>
    </timestamp>
    <lps331>
      <t>24,5</t>
      <p>1011</p>
    </lps331>
    <hdc1080>
      <t>25,82275</t>
      <hum>34</hum>
    </hdc1080>
  </report>
  <report id="35">
    <timestamp>
      <date>2019.02.24</date>
      <time>22:07:11.773</time>
    </timestamp>
    <lps331>
      <t>24,5</t>
      <p>1011</p>
    </lps331>
    <hdc1080>
      <t>25,83282</t>
      <hum>33</hum>
    </hdc1080>
  </report>
  <report id="36">
    <timestamp>
      <date>2019.02.24</date>
      <time>22:07:12.867</time>
    </timestamp>
    <lps331>
      <t>24,5</t>
      <p>1010</p>
    </lps331>
    <hdc1080>
      <t>25,83282</t>
      <hum>33</hum>
    </hdc1080>
  </report>
  <report id="37">
    <timestamp>
      <date>2019.02.24</date>
      <time>22:07:13.957</time>
    </timestamp>
    <lps331>
      <t>24,5</t>
      <p>1011</p>
    </lps331>
    <hdc1080>
      <t>25,85297</t>
      <hum>33</hum>
    </hdc1080>
  </report>
  <report id="38">
    <timestamp>
      <date>2019.02.24</date>
      <time>22:07:15.050</time>
    </timestamp>
    <lps331>
      <t>24,5</t>
      <p>1011</p>
    </lps331>
    <hdc1080>
      <t>25,85297</t>
      <hum>33</hum>
    </hdc1080>
  </report>
  <report id="39">
    <timestamp>
      <date>2019.02.24</date>
      <time>22:07:15.636</time>
    </timestamp>
    <lps331>
      <t>24,5</t>
      <p>1011</p>
    </lps331>
    <hdc1080>
      <t>25,87311</t>
      <hum>33</hum>
    </hdc1080>
  </report>
  <report id="40">
    <timestamp>
      <date>2019.02.24</date>
      <time>22:07:16.730</time>
    </timestamp>
    <lps331>
      <t>24,5</t>
      <p>1011</p>
    </lps331>
    <hdc1080>
      <t>25,83282</t>
      <hum>33</hum>
    </hdc1080>
  </report>
  <report id="41">
    <timestamp>
      <date>2019.02.24</date>
      <time>22:07:17.824</time>
    </timestamp>
    <lps331>
      <t>24,5</t>
      <p>1011</p>
    </lps331>
    <hdc1080>
      <t>25,85297</t>
      <hum>33</hum>
    </hdc1080>
  </report>
  <report id="42">
    <timestamp>
      <date>2019.02.24</date>
      <time>22:07:18.917</time>
    </timestamp>
    <lps331>
      <t>24,5</t>
      <p>1011</p>
    </lps331>
    <hdc1080>
      <t>25,83282</t>
      <hum>34</hum>
    </hdc1080>
  </report>
  <report id="43">
    <timestamp>
      <date>2019.02.24</date>
      <time>22:07:20.007</time>
    </timestamp>
    <lps331>
      <t>24,5</t>
      <p>1011</p>
    </lps331>
    <hdc1080>
      <t>25,85297</t>
      <hum>34</hum>
    </hdc1080>
  </report>
  <report id="44">
    <timestamp>
      <date>2019.02.24</date>
      <time>22:07:20.597</time>
    </timestamp>
    <lps331>
      <t>24,5</t>
      <p>1011</p>
    </lps331>
    <hdc1080>
      <t>25,85297</t>
      <hum>34</hum>
    </hdc1080>
  </report>
  <report id="45">
    <timestamp>
      <date>2019.02.24</date>
      <time>22:07:21.687</time>
    </timestamp>
    <lps331>
      <t>24,5</t>
      <p>1011</p>
    </lps331>
    <hdc1080>
      <t>25,85297</t>
      <hum>34</hum>
    </hdc1080>
  </report>
  <report id="46">
    <timestamp>
      <date>2019.02.24</date>
      <time>22:07:22.781</time>
    </timestamp>
    <lps331>
      <t>24,5</t>
      <p>1011</p>
    </lps331>
    <hdc1080>
      <t>25,85297</t>
      <hum>34</hum>
    </hdc1080>
  </report>
  <report id="47">
    <timestamp>
      <date>2019.02.24</date>
      <time>22:07:23.875</time>
    </timestamp>
    <lps331>
      <t>24,5</t>
      <p>1011</p>
    </lps331>
    <hdc1080>
      <t>25,85297</t>
      <hum>34</hum>
    </hdc1080>
  </report>
  <report id="48">
    <timestamp>
      <date>2019.02.24</date>
      <time>22:07:24.968</time>
    </timestamp>
    <lps331>
      <t>24,5</t>
      <p>1011</p>
    </lps331>
    <hdc1080>
      <t>25,85297</t>
      <hum>33</hum>
    </hdc1080>
  </report>
  <report id="49">
    <timestamp>
      <date>2019.02.24</date>
      <time>22:07:26.062</time>
    </timestamp>
    <lps331>
      <t>24,5</t>
      <p>1011</p>
    </lps331>
    <hdc1080>
      <t>25,85297</t>
      <hum>33</hum>
    </hdc1080>
  </report>
  <report id="50">
    <timestamp>
      <date>2019.02.24</date>
      <time>22:07:26.648</time>
    </timestamp>
    <lps331>
      <t>24,5</t>
      <p>1011</p>
    </lps331>
    <hdc1080>
      <t>25,85297</t>
      <hum>33</hum>
    </hdc1080>
  </report>
  <report id="51">
    <timestamp>
      <date>2019.02.24</date>
      <time>22:07:27.742</time>
    </timestamp>
    <lps331>
      <t>24,5</t>
      <p>1011</p>
    </lps331>
    <hdc1080>
      <t>25,85297</t>
      <hum>33</hum>
    </hdc1080>
  </report>
  <report id="52">
    <timestamp>
      <date>2019.02.24</date>
      <time>22:07:28.835</time>
    </timestamp>
    <lps331>
      <t>24,5</t>
      <p>1011</p>
    </lps331>
    <hdc1080>
      <t>25,85297</t>
      <hum>33</hum>
    </hdc1080>
  </report>
  <report id="53">
    <timestamp>
      <date>2019.02.24</date>
      <time>22:07:29.929</time>
    </timestamp>
    <lps331>
      <t>24,5</t>
      <p>1011</p>
    </lps331>
    <hdc1080>
      <t>25,85297</t>
      <hum>33</hum>
    </hdc1080>
  </report>
  <report id="54">
    <timestamp>
      <date>2019.02.24</date>
      <time>22:07:31.023</time>
    </timestamp>
    <lps331>
      <t>24,5</t>
      <p>1011</p>
    </lps331>
    <hdc1080>
      <t>25,82275</t>
      <hum>33</hum>
    </hdc1080>
  </report>
  <report id="55">
    <timestamp>
      <date>2019.02.24</date>
      <time>22:07:31.609</time>
    </timestamp>
    <lps331>
      <t>24,5</t>
      <p>1011</p>
    </lps331>
    <hdc1080>
      <t>25,85297</t>
      <hum>33</hum>
    </hdc1080>
  </report>
  <report id="56">
    <timestamp>
      <date>2019.02.24</date>
      <time>22:07:32.703</time>
    </timestamp>
    <lps331>
      <t>24,5</t>
      <p>1011</p>
    </lps331>
    <hdc1080>
      <t>25,85297</t>
      <hum>33</hum>
    </hdc1080>
  </report>
  <report id="57">
    <timestamp>
      <date>2019.02.24</date>
      <time>22:07:33.796</time>
    </timestamp>
    <lps331>
      <t>24,5</t>
      <p>1011</p>
    </lps331>
    <hdc1080>
      <t>25,83282</t>
      <hum>33</hum>
    </hdc1080>
  </report>
  <report id="58">
    <timestamp>
      <date>2019.02.24</date>
      <time>22:07:34.890</time>
    </timestamp>
    <lps331>
      <t>24,5</t>
      <p>1011</p>
    </lps331>
    <hdc1080>
      <t>25,85297</t>
      <hum>33</hum>
    </hdc1080>
  </report>
  <report id="59">
    <timestamp>
      <date>2019.02.24</date>
      <time>22:07:35.984</time>
    </timestamp>
    <lps331>
      <t>24,5</t>
      <p>1011</p>
    </lps331>
    <hdc1080>
      <t>25,85297</t>
      <hum>33</hum>
    </hdc1080>
  </report>
  <report id="60">
    <timestamp>
      <date>2019.02.24</date>
      <time>22:07:37.074</time>
    </timestamp>
    <lps331>
      <t>24,5</t>
      <p>1011</p>
    </lps331>
    <hdc1080>
      <t>25,85297</t>
      <hum>33</hum>
    </hdc1080>
  </report>
  <report id="61">
    <timestamp>
      <date>2019.02.24</date>
      <time>22:07:37.664</time>
    </timestamp>
    <lps331>
      <t>24,5</t>
      <p>1011</p>
    </lps331>
    <hdc1080>
      <t>25,83282</t>
      <hum>33</hum>
    </hdc1080>
  </report>
  <report id="62">
    <timestamp>
      <date>2019.02.24</date>
      <time>22:07:38.757</time>
    </timestamp>
    <lps331>
      <t>24,5</t>
      <p>1011</p>
    </lps331>
    <hdc1080>
      <t>25,83282</t>
      <hum>33</hum>
    </hdc1080>
  </report>
  <report id="63">
    <timestamp>
      <date>2019.02.24</date>
      <time>22:07:39.847</time>
    </timestamp>
    <lps331>
      <t>24,5</t>
      <p>1011</p>
    </lps331>
    <hdc1080>
      <t>25,83282</t>
      <hum>34</hum>
    </hdc1080>
  </report>
  <report id="64">
    <timestamp>
      <date>2019.02.24</date>
      <time>22:07:40.941</time>
    </timestamp>
    <lps331>
      <t>24,5</t>
      <p>1011</p>
    </lps331>
    <hdc1080>
      <t>25,85297</t>
      <hum>34</hum>
    </hdc1080>
  </report>
  <report id="65">
    <timestamp>
      <date>2019.02.24</date>
      <time>22:07:42.035</time>
    </timestamp>
    <lps331>
      <t>24,5</t>
      <p>1011</p>
    </lps331>
    <hdc1080>
      <t>25,83282</t>
      <hum>34</hum>
    </hdc1080>
  </report>
  <report id="66">
    <timestamp>
      <date>2019.02.24</date>
      <time>22:07:42.621</time>
    </timestamp>
    <lps331>
      <t>24,5</t>
      <p>1011</p>
    </lps331>
    <hdc1080>
      <t>25,87311</t>
      <hum>34</hum>
    </hdc1080>
  </report>
  <report id="67">
    <timestamp>
      <date>2019.02.24</date>
      <time>22:07:43.714</time>
    </timestamp>
    <lps331>
      <t>24,5</t>
      <p>1011</p>
    </lps331>
    <hdc1080>
      <t>25,83282</t>
      <hum>34</hum>
    </hdc1080>
  </report>
  <report id="68">
    <timestamp>
      <date>2019.02.24</date>
      <time>22:07:44.808</time>
    </timestamp>
    <lps331>
      <t>24,5</t>
      <p>1011</p>
    </lps331>
    <hdc1080>
      <t>25,85297</t>
      <hum>34</hum>
    </hdc1080>
  </report>
  <report id="69">
    <timestamp>
      <date>2019.02.24</date>
      <time>22:07:45.902</time>
    </timestamp>
    <lps331>
      <t>24,5</t>
      <p>1011</p>
    </lps331>
    <hdc1080>
      <t>25,85297</t>
      <hum>34</hum>
    </hdc1080>
  </report>
  <report id="70">
    <timestamp>
      <date>2019.02.24</date>
      <time>22:07:46.992</time>
    </timestamp>
    <lps331>
      <t>24,5</t>
      <p>1011</p>
    </lps331>
    <hdc1080>
      <t>25,85297</t>
      <hum>34</hum>
    </hdc1080>
  </report>
  <report id="71">
    <timestamp>
      <date>2019.02.24</date>
      <time>22:07:48.085</time>
    </timestamp>
    <lps331>
      <t>24,5</t>
      <p>1011</p>
    </lps331>
    <hdc1080>
      <t>25,87311</t>
      <hum>34</hum>
    </hdc1080>
  </report>
  <report id="72">
    <timestamp>
      <date>2019.02.24</date>
      <time>22:07:48.675</time>
    </timestamp>
    <lps331>
      <t>24,5</t>
      <p>1011</p>
    </lps331>
    <hdc1080>
      <t>25,87311</t>
      <hum>34</hum>
    </hdc1080>
  </report>
  <report id="73">
    <timestamp>
      <date>2019.02.24</date>
      <time>22:07:49.765</time>
    </timestamp>
    <lps331>
      <t>24,5</t>
      <p>1011</p>
    </lps331>
    <hdc1080>
      <t>25,85297</t>
      <hum>34</hum>
    </hdc1080>
  </report>
  <report id="74">
    <timestamp>
      <date>2019.02.24</date>
      <time>22:07:50.859</time>
    </timestamp>
    <lps331>
      <t>24,5</t>
      <p>1011</p>
    </lps331>
    <hdc1080>
      <t>25,85297</t>
      <hum>34</hum>
    </hdc1080>
  </report>
  <report id="75">
    <timestamp>
      <date>2019.02.24</date>
      <time>22:07:51.953</time>
    </timestamp>
    <lps331>
      <t>24,5</t>
      <p>1011</p>
    </lps331>
    <hdc1080>
      <t>25,87311</t>
      <hum>34</hum>
    </hdc1080>
  </report>
  <report id="76">
    <timestamp>
      <date>2019.02.24</date>
      <time>22:07:53.046</time>
    </timestamp>
    <lps331>
      <t>24,5</t>
      <p>1011</p>
    </lps331>
    <hdc1080>
      <t>25,85297</t>
      <hum>33</hum>
    </hdc1080>
  </report>
  <report id="77">
    <timestamp>
      <date>2019.02.24</date>
      <time>22:07:53.636</time>
    </timestamp>
    <lps331>
      <t>24,5</t>
      <p>1011</p>
    </lps331>
    <hdc1080>
      <t>25,87311</t>
      <hum>33</hum>
    </hdc1080>
  </report>
  <report id="78">
    <timestamp>
      <date>2019.02.24</date>
      <time>22:07:54.726</time>
    </timestamp>
    <lps331>
      <t>24,5</t>
      <p>1011</p>
    </lps331>
    <hdc1080>
      <t>25,85297</t>
      <hum>33</hum>
    </hdc1080>
  </report>
  <report id="79">
    <timestamp>
      <date>2019.02.24</date>
      <time>22:07:55.820</time>
    </timestamp>
    <lps331>
      <t>24,5</t>
      <p>1011</p>
    </lps331>
    <hdc1080>
      <t>25,87311</t>
      <hum>33</hum>
    </hdc1080>
  </report>
  <report id="80">
    <timestamp>
      <date>2019.02.24</date>
      <time>22:07:56.914</time>
    </timestamp>
    <lps331>
      <t>24,5</t>
      <p>1011</p>
    </lps331>
    <hdc1080>
      <t>25,87311</t>
      <hum>33</hum>
    </hdc1080>
  </report>
  <report id="81">
    <timestamp>
      <date>2019.02.24</date>
      <time>22:07:58.007</time>
    </timestamp>
    <lps331>
      <t>24,5</t>
      <p>1011</p>
    </lps331>
    <hdc1080>
      <t>25,85297</t>
      <hum>33</hum>
    </hdc1080>
  </report>
  <report id="82">
    <timestamp>
      <date>2019.02.24</date>
      <time>22:07:58.597</time>
    </timestamp>
    <lps331>
      <t>24,5</t>
      <p>1010</p>
    </lps331>
    <hdc1080>
      <t>25,85297</t>
      <hum>33</hum>
    </hdc1080>
  </report>
  <report id="83">
    <timestamp>
      <date>2019.02.24</date>
      <time>22:07:59.691</time>
    </timestamp>
    <lps331>
      <t>24,5</t>
      <p>1011</p>
    </lps331>
    <hdc1080>
      <t>25,85297</t>
      <hum>33</hum>
    </hdc1080>
  </report>
</tph_report>