<?xml version="1.0" encoding="UTF-8"?>
<tph_report>
  <report id="0">
    <timestamp>
      <date>2019.02.24</date>
      <time>21:55:20.726</time>
    </timestamp>
    <lps331>
      <t>24,5</t>
      <p>1011</p>
    </lps331>
    <hdc1080>
      <t>25,7724</t>
      <hum>34</hum>
    </hdc1080>
  </report>
  <report id="1">
    <timestamp>
      <date>2019.02.24</date>
      <time>21:55:21.820</time>
    </timestamp>
    <lps331>
      <t>24,5</t>
      <p>1011</p>
    </lps331>
    <hdc1080>
      <t>25,76233</t>
      <hum>34</hum>
    </hdc1080>
  </report>
  <report id="2">
    <timestamp>
      <date>2019.02.24</date>
      <time>21:55:22.914</time>
    </timestamp>
    <lps331>
      <t>24,5</t>
      <p>1011</p>
    </lps331>
    <hdc1080>
      <t>25,76233</t>
      <hum>34</hum>
    </hdc1080>
  </report>
  <report id="3">
    <timestamp>
      <date>2019.02.24</date>
      <time>21:55:24.007</time>
    </timestamp>
    <lps331>
      <t>24,5</t>
      <p>1011</p>
    </lps331>
    <hdc1080>
      <t>25,75226</t>
      <hum>34</hum>
    </hdc1080>
  </report>
  <report id="4">
    <timestamp>
      <date>2019.02.24</date>
      <time>21:55:24.593</time>
    </timestamp>
    <lps331>
      <t>24,5</t>
      <p>1011</p>
    </lps331>
    <hdc1080>
      <t>25,76233</t>
      <hum>33</hum>
    </hdc1080>
  </report>
  <report id="5">
    <timestamp>
      <date>2019.02.24</date>
      <time>21:55:25.687</time>
    </timestamp>
    <lps331>
      <t>24,5</t>
      <p>1011</p>
    </lps331>
    <hdc1080>
      <t>25,76233</t>
      <hum>33</hum>
    </hdc1080>
  </report>
  <report id="6">
    <timestamp>
      <date>2019.02.24</date>
      <time>21:55:26.781</time>
    </timestamp>
    <lps331>
      <t>24,5</t>
      <p>1011</p>
    </lps331>
    <hdc1080>
      <t>25,76233</t>
      <hum>33</hum>
    </hdc1080>
  </report>
  <report id="7">
    <timestamp>
      <date>2019.02.24</date>
      <time>21:55:27.875</time>
    </timestamp>
    <lps331>
      <t>24,5</t>
      <p>1011</p>
    </lps331>
    <hdc1080>
      <t>25,76233</t>
      <hum>33</hum>
    </hdc1080>
  </report>
  <report id="8">
    <timestamp>
      <date>2019.02.24</date>
      <time>21:55:28.964</time>
    </timestamp>
    <lps331>
      <t>24,5</t>
      <p>1011</p>
    </lps331>
    <hdc1080>
      <t>25,76233</t>
      <hum>33</hum>
    </hdc1080>
  </report>
  <report id="9">
    <timestamp>
      <date>2019.02.24</date>
      <time>21:55:30.058</time>
    </timestamp>
    <lps331>
      <t>24,5</t>
      <p>1011</p>
    </lps331>
    <hdc1080>
      <t>25,75226</t>
      <hum>33</hum>
    </hdc1080>
  </report>
  <report id="10">
    <timestamp>
      <date>2019.02.24</date>
      <time>21:55:30.648</time>
    </timestamp>
    <lps331>
      <t>24,5</t>
      <p>1011</p>
    </lps331>
    <hdc1080>
      <t>25,76233</t>
      <hum>33</hum>
    </hdc1080>
  </report>
  <report id="11">
    <timestamp>
      <date>2019.02.24</date>
      <time>21:55:31.742</time>
    </timestamp>
    <lps331>
      <t>24,5</t>
      <p>1011</p>
    </lps331>
    <hdc1080>
      <t>25,76233</t>
      <hum>33</hum>
    </hdc1080>
  </report>
  <report id="12">
    <timestamp>
      <date>2019.02.24</date>
      <time>21:55:32.835</time>
    </timestamp>
    <lps331>
      <t>24,5</t>
      <p>1011</p>
    </lps331>
    <hdc1080>
      <t>25,76233</t>
      <hum>33</hum>
    </hdc1080>
  </report>
  <report id="13">
    <timestamp>
      <date>2019.02.24</date>
      <time>21:55:33.929</time>
    </timestamp>
    <lps331>
      <t>24,5</t>
      <p>1011</p>
    </lps331>
    <hdc1080>
      <t>25,76233</t>
      <hum>33</hum>
    </hdc1080>
  </report>
  <report id="14">
    <timestamp>
      <date>2019.02.24</date>
      <time>21:55:35.023</time>
    </timestamp>
    <lps331>
      <t>24,5</t>
      <p>1011</p>
    </lps331>
    <hdc1080>
      <t>25,76233</t>
      <hum>34</hum>
    </hdc1080>
  </report>
  <report id="15">
    <timestamp>
      <date>2019.02.24</date>
      <time>21:55:35.609</time>
    </timestamp>
    <lps331>
      <t>24,5</t>
      <p>1011</p>
    </lps331>
    <hdc1080>
      <t>25,79254</t>
      <hum>34</hum>
    </hdc1080>
  </report>
  <report id="16">
    <timestamp>
      <date>2019.02.24</date>
      <time>21:55:36.703</time>
    </timestamp>
    <lps331>
      <t>24,5</t>
      <p>1011</p>
    </lps331>
    <hdc1080>
      <t>25,76233</t>
      <hum>35</hum>
    </hdc1080>
  </report>
  <report id="17">
    <timestamp>
      <date>2019.02.24</date>
      <time>21:55:37.796</time>
    </timestamp>
    <lps331>
      <t>24,5</t>
      <p>1011</p>
    </lps331>
    <hdc1080>
      <t>25,76233</t>
      <hum>35</hum>
    </hdc1080>
  </report>
  <report id="18">
    <timestamp>
      <date>2019.02.24</date>
      <time>21:55:38.890</time>
    </timestamp>
    <lps331>
      <t>24,5</t>
      <p>1011</p>
    </lps331>
    <hdc1080>
      <t>25,76233</t>
      <hum>35</hum>
    </hdc1080>
  </report>
  <report id="19">
    <timestamp>
      <date>2019.02.24</date>
      <time>21:55:39.984</time>
    </timestamp>
    <lps331>
      <t>24,5</t>
      <p>1011</p>
    </lps331>
    <hdc1080>
      <t>25,7724</t>
      <hum>35</hum>
    </hdc1080>
  </report>
  <report id="20">
    <timestamp>
      <date>2019.02.24</date>
      <time>21:55:41.078</time>
    </timestamp>
    <lps331>
      <t>24,5</t>
      <p>1011</p>
    </lps331>
    <hdc1080>
      <t>25,76233</t>
      <hum>35</hum>
    </hdc1080>
  </report>
  <report id="21">
    <timestamp>
      <date>2019.02.24</date>
      <time>21:55:41.664</time>
    </timestamp>
    <lps331>
      <t>24,5</t>
      <p>1011</p>
    </lps331>
    <hdc1080>
      <t>25,76233</t>
      <hum>35</hum>
    </hdc1080>
  </report>
  <report id="22">
    <timestamp>
      <date>2019.02.24</date>
      <time>21:55:42.757</time>
    </timestamp>
    <lps331>
      <t>24,5</t>
      <p>1011</p>
    </lps331>
    <hdc1080>
      <t>25,76233</t>
      <hum>35</hum>
    </hdc1080>
  </report>
  <report id="23">
    <timestamp>
      <date>2019.02.24</date>
      <time>21:55:43.851</time>
    </timestamp>
    <lps331>
      <t>24,5</t>
      <p>1011</p>
    </lps331>
    <hdc1080>
      <t>25,79254</t>
      <hum>35</hum>
    </hdc1080>
  </report>
  <report id="24">
    <timestamp>
      <date>2019.02.24</date>
      <time>21:55:44.945</time>
    </timestamp>
    <lps331>
      <t>24,5</t>
      <p>1011</p>
    </lps331>
    <hdc1080>
      <t>25,7724</t>
      <hum>35</hum>
    </hdc1080>
  </report>
  <report id="25">
    <timestamp>
      <date>2019.02.24</date>
      <time>21:55:46.039</time>
    </timestamp>
    <lps331>
      <t>24,5</t>
      <p>1011</p>
    </lps331>
    <hdc1080>
      <t>25,7724</t>
      <hum>34</hum>
    </hdc1080>
  </report>
  <report id="26">
    <timestamp>
      <date>2019.02.24</date>
      <time>21:55:46.628</time>
    </timestamp>
    <lps331>
      <t>24,5</t>
      <p>1011</p>
    </lps331>
    <hdc1080>
      <t>25,76233</t>
      <hum>34</hum>
    </hdc1080>
  </report>
  <report id="27">
    <timestamp>
      <date>2019.02.24</date>
      <time>21:55:47.722</time>
    </timestamp>
    <lps331>
      <t>24,5</t>
      <p>1011</p>
    </lps331>
    <hdc1080>
      <t>25,7724</t>
      <hum>34</hum>
    </hdc1080>
  </report>
  <report id="28">
    <timestamp>
      <date>2019.02.24</date>
      <time>21:55:48.816</time>
    </timestamp>
    <lps331>
      <t>24,5</t>
      <p>1011</p>
    </lps331>
    <hdc1080>
      <t>25,7724</t>
      <hum>34</hum>
    </hdc1080>
  </report>
  <report id="29">
    <timestamp>
      <date>2019.02.24</date>
      <time>21:55:49.910</time>
    </timestamp>
    <lps331>
      <t>24,5</t>
      <p>1011</p>
    </lps331>
    <hdc1080>
      <t>25,76233</t>
      <hum>34</hum>
    </hdc1080>
  </report>
  <report id="30">
    <timestamp>
      <date>2019.02.24</date>
      <time>21:55:51.000</time>
    </timestamp>
    <lps331>
      <t>24,5</t>
      <p>1011</p>
    </lps331>
    <hdc1080>
      <t>25,79254</t>
      <hum>33</hum>
    </hdc1080>
  </report>
  <report id="31">
    <timestamp>
      <date>2019.02.24</date>
      <time>21:55:51.589</time>
    </timestamp>
    <lps331>
      <t>24,5</t>
      <p>1011</p>
    </lps331>
    <hdc1080>
      <t>25,7724</t>
      <hum>33</hum>
    </hdc1080>
  </report>
  <report id="32">
    <timestamp>
      <date>2019.02.24</date>
      <time>21:55:52.683</time>
    </timestamp>
    <lps331>
      <t>24,5</t>
      <p>1011</p>
    </lps331>
    <hdc1080>
      <t>25,76233</t>
      <hum>33</hum>
    </hdc1080>
  </report>
  <report id="33">
    <timestamp>
      <date>2019.02.24</date>
      <time>21:55:53.777</time>
    </timestamp>
    <lps331>
      <t>24,5</t>
      <p>1011</p>
    </lps331>
    <hdc1080>
      <t>25,7724</t>
      <hum>33</hum>
    </hdc1080>
  </report>
  <report id="34">
    <timestamp>
      <date>2019.02.24</date>
      <time>21:55:54.871</time>
    </timestamp>
    <lps331>
      <t>24,5</t>
      <p>1011</p>
    </lps331>
    <hdc1080>
      <t>25,75226</t>
      <hum>34</hum>
    </hdc1080>
  </report>
  <report id="35">
    <timestamp>
      <date>2019.02.24</date>
      <time>21:55:55.964</time>
    </timestamp>
    <lps331>
      <t>24,5</t>
      <p>1011</p>
    </lps331>
    <hdc1080>
      <t>25,7724</t>
      <hum>34</hum>
    </hdc1080>
  </report>
  <report id="36">
    <timestamp>
      <date>2019.02.24</date>
      <time>21:55:57.058</time>
    </timestamp>
    <lps331>
      <t>24,5</t>
      <p>1011</p>
    </lps331>
    <hdc1080>
      <t>25,79254</t>
      <hum>34</hum>
    </hdc1080>
  </report>
  <report id="37">
    <timestamp>
      <date>2019.02.24</date>
      <time>21:55:57.648</time>
    </timestamp>
    <lps331>
      <t>24,5</t>
      <p>1011</p>
    </lps331>
    <hdc1080>
      <t>25,79254</t>
      <hum>34</hum>
    </hdc1080>
  </report>
  <report id="38">
    <timestamp>
      <date>2019.02.24</date>
      <time>21:55:58.742</time>
    </timestamp>
    <lps331>
      <t>24,5</t>
      <p>1011</p>
    </lps331>
    <hdc1080>
      <t>25,76233</t>
      <hum>34</hum>
    </hdc1080>
  </report>
  <report id="39">
    <timestamp>
      <date>2019.02.24</date>
      <time>21:55:59.835</time>
    </timestamp>
    <lps331>
      <t>24,5</t>
      <p>1011</p>
    </lps331>
    <hdc1080>
      <t>25,7724</t>
      <hum>34</hum>
    </hdc1080>
  </report>
  <report id="40">
    <timestamp>
      <date>2019.02.24</date>
      <time>21:56:00.929</time>
    </timestamp>
    <lps331>
      <t>24,5</t>
      <p>1011</p>
    </lps331>
    <hdc1080>
      <t>25,7724</t>
      <hum>34</hum>
    </hdc1080>
  </report>
  <report id="41">
    <timestamp>
      <date>2019.02.24</date>
      <time>21:56:02.023</time>
    </timestamp>
    <lps331>
      <t>24,5</t>
      <p>1011</p>
    </lps331>
    <hdc1080>
      <t>25,76233</t>
      <hum>34</hum>
    </hdc1080>
  </report>
  <report id="42">
    <timestamp>
      <date>2019.02.24</date>
      <time>21:56:02.609</time>
    </timestamp>
    <lps331>
      <t>24,5</t>
      <p>1011</p>
    </lps331>
    <hdc1080>
      <t>25,7724</t>
      <hum>34</hum>
    </hdc1080>
  </report>
  <report id="43">
    <timestamp>
      <date>2019.02.24</date>
      <time>21:56:03.703</time>
    </timestamp>
    <lps331>
      <t>24,5</t>
      <p>1011</p>
    </lps331>
    <hdc1080>
      <t>25,7724</t>
      <hum>34</hum>
    </hdc1080>
  </report>
  <report id="44">
    <timestamp>
      <date>2019.02.24</date>
      <time>21:56:04.800</time>
    </timestamp>
    <lps331>
      <t>24,5</t>
      <p>1011</p>
    </lps331>
    <hdc1080>
      <t>25,7724</t>
      <hum>34</hum>
    </hdc1080>
  </report>
  <report id="45">
    <timestamp>
      <date>2019.02.24</date>
      <time>21:56:05.890</time>
    </timestamp>
    <lps331>
      <t>24,5</t>
      <p>1011</p>
    </lps331>
    <hdc1080>
      <t>25,7724</t>
      <hum>34</hum>
    </hdc1080>
  </report>
  <report id="46">
    <timestamp>
      <date>2019.02.24</date>
      <time>21:56:06.984</time>
    </timestamp>
    <lps331>
      <t>24,5</t>
      <p>1011</p>
    </lps331>
    <hdc1080>
      <t>25,7724</t>
      <hum>34</hum>
    </hdc1080>
  </report>
  <report id="47">
    <timestamp>
      <date>2019.02.24</date>
      <time>21:56:08.078</time>
    </timestamp>
    <lps331>
      <t>24,5</t>
      <p>1011</p>
    </lps331>
    <hdc1080>
      <t>25,7724</t>
      <hum>33</hum>
    </hdc1080>
  </report>
  <report id="48">
    <timestamp>
      <date>2019.02.24</date>
      <time>21:56:08.667</time>
    </timestamp>
    <lps331>
      <t>24,5</t>
      <p>1011</p>
    </lps331>
    <hdc1080>
      <t>25,7724</t>
      <hum>33</hum>
    </hdc1080>
  </report>
  <report id="49">
    <timestamp>
      <date>2019.02.24</date>
      <time>21:56:09.761</time>
    </timestamp>
    <lps331>
      <t>24,5</t>
      <p>1011</p>
    </lps331>
    <hdc1080>
      <t>25,76233</t>
      <hum>33</hum>
    </hdc1080>
  </report>
  <report id="50">
    <timestamp>
      <date>2019.02.24</date>
      <time>21:56:10.855</time>
    </timestamp>
    <lps331>
      <t>24,5</t>
      <p>1011</p>
    </lps331>
    <hdc1080>
      <t>25,76233</t>
      <hum>33</hum>
    </hdc1080>
  </report>
  <report id="51">
    <timestamp>
      <date>2019.02.24</date>
      <time>21:56:11.949</time>
    </timestamp>
    <lps331>
      <t>24,5</t>
      <p>1011</p>
    </lps331>
    <hdc1080>
      <t>25,7724</t>
      <hum>33</hum>
    </hdc1080>
  </report>
  <report id="52">
    <timestamp>
      <date>2019.02.24</date>
      <time>21:56:13.039</time>
    </timestamp>
    <lps331>
      <t>24,5</t>
      <p>1011</p>
    </lps331>
    <hdc1080>
      <t>25,7724</t>
      <hum>33</hum>
    </hdc1080>
  </report>
  <report id="53">
    <timestamp>
      <date>2019.02.24</date>
      <time>21:56:13.628</time>
    </timestamp>
    <lps331>
      <t>24,5</t>
      <p>1011</p>
    </lps331>
    <hdc1080>
      <t>25,76233</t>
      <hum>33</hum>
    </hdc1080>
  </report>
  <report id="54">
    <timestamp>
      <date>2019.02.24</date>
      <time>21:56:14.722</time>
    </timestamp>
    <lps331>
      <t>24,5</t>
      <p>1011</p>
    </lps331>
    <hdc1080>
      <t>25,7724</t>
      <hum>33</hum>
    </hdc1080>
  </report>
  <report id="55">
    <timestamp>
      <date>2019.02.24</date>
      <time>21:56:15.812</time>
    </timestamp>
    <lps331>
      <t>24,5</t>
      <p>1011</p>
    </lps331>
    <hdc1080>
      <t>25,76233</t>
      <hum>33</hum>
    </hdc1080>
  </report>
  <report id="56">
    <timestamp>
      <date>2019.02.24</date>
      <time>21:56:16.906</time>
    </timestamp>
    <lps331>
      <t>24,5</t>
      <p>1011</p>
    </lps331>
    <hdc1080>
      <t>25,76233</t>
      <hum>33</hum>
    </hdc1080>
  </report>
  <report id="57">
    <timestamp>
      <date>2019.02.24</date>
      <time>21:56:18.000</time>
    </timestamp>
    <lps331>
      <t>24,5</t>
      <p>1011</p>
    </lps331>
    <hdc1080>
      <t>25,7724</t>
      <hum>33</hum>
    </hdc1080>
  </report>
  <report id="58">
    <timestamp>
      <date>2019.02.24</date>
      <time>21:56:18.589</time>
    </timestamp>
    <lps331>
      <t>24,5</t>
      <p>1011</p>
    </lps331>
    <hdc1080>
      <t>25,79254</t>
      <hum>33</hum>
    </hdc1080>
  </report>
  <report id="59">
    <timestamp>
      <date>2019.02.24</date>
      <time>21:56:19.683</time>
    </timestamp>
    <lps331>
      <t>24,5</t>
      <p>1011</p>
    </lps331>
    <hdc1080>
      <t>25,76233</t>
      <hum>33</hum>
    </hdc1080>
  </report>
  <report id="60">
    <timestamp>
      <date>2019.02.24</date>
      <time>21:56:20.777</time>
    </timestamp>
    <lps331>
      <t>24,5</t>
      <p>1011</p>
    </lps331>
    <hdc1080>
      <t>25,76233</t>
      <hum>33</hum>
    </hdc1080>
  </report>
  <report id="61">
    <timestamp>
      <date>2019.02.24</date>
      <time>21:56:21.871</time>
    </timestamp>
    <lps331>
      <t>24,5</t>
      <p>1011</p>
    </lps331>
    <hdc1080>
      <t>25,7724</t>
      <hum>33</hum>
    </hdc1080>
  </report>
  <report id="62">
    <timestamp>
      <date>2019.02.24</date>
      <time>21:56:22.964</time>
    </timestamp>
    <lps331>
      <t>24,5</t>
      <p>1011</p>
    </lps331>
    <hdc1080>
      <t>25,76233</t>
      <hum>33</hum>
    </hdc1080>
  </report>
  <report id="63">
    <timestamp>
      <date>2019.02.24</date>
      <time>21:56:24.058</time>
    </timestamp>
    <lps331>
      <t>24,5</t>
      <p>1011</p>
    </lps331>
    <hdc1080>
      <t>25,79254</t>
      <hum>33</hum>
    </hdc1080>
  </report>
  <report id="64">
    <timestamp>
      <date>2019.02.24</date>
      <time>21:56:24.644</time>
    </timestamp>
    <lps331>
      <t>24,5</t>
      <p>1011</p>
    </lps331>
    <hdc1080>
      <t>25,7724</t>
      <hum>33</hum>
    </hdc1080>
  </report>
  <report id="65">
    <timestamp>
      <date>2019.02.24</date>
      <time>21:56:25.738</time>
    </timestamp>
    <lps331>
      <t>24,5</t>
      <p>1011</p>
    </lps331>
    <hdc1080>
      <t>25,7724</t>
      <hum>33</hum>
    </hdc1080>
  </report>
  <report id="66">
    <timestamp>
      <date>2019.02.24</date>
      <time>21:56:26.832</time>
    </timestamp>
    <lps331>
      <t>24,5</t>
      <p>1011</p>
    </lps331>
    <hdc1080>
      <t>25,76233</t>
      <hum>33</hum>
    </hdc1080>
  </report>
  <report id="67">
    <timestamp>
      <date>2019.02.24</date>
      <time>21:56:27.925</time>
    </timestamp>
    <lps331>
      <t>24,5</t>
      <p>1011</p>
    </lps331>
    <hdc1080>
      <t>25,7724</t>
      <hum>33</hum>
    </hdc1080>
  </report>
  <report id="68">
    <timestamp>
      <date>2019.02.24</date>
      <time>21:56:29.019</time>
    </timestamp>
    <lps331>
      <t>24,5</t>
      <p>1011</p>
    </lps331>
    <hdc1080>
      <t>25,7724</t>
      <hum>33</hum>
    </hdc1080>
  </report>
  <report id="69">
    <timestamp>
      <date>2019.02.24</date>
      <time>21:56:29.609</time>
    </timestamp>
    <lps331>
      <t>24,5</t>
      <p>1011</p>
    </lps331>
    <hdc1080>
      <t>25,7724</t>
      <hum>33</hum>
    </hdc1080>
  </report>
  <report id="70">
    <timestamp>
      <date>2019.02.24</date>
      <time>21:56:30.703</time>
    </timestamp>
    <lps331>
      <t>24,5</t>
      <p>1011</p>
    </lps331>
    <hdc1080>
      <t>25,79254</t>
      <hum>33</hum>
    </hdc1080>
  </report>
  <report id="71">
    <timestamp>
      <date>2019.02.24</date>
      <time>21:56:31.796</time>
    </timestamp>
    <lps331>
      <t>24,5</t>
      <p>1011</p>
    </lps331>
    <hdc1080>
      <t>25,79254</t>
      <hum>33</hum>
    </hdc1080>
  </report>
  <report id="72">
    <timestamp>
      <date>2019.02.24</date>
      <time>21:56:32.890</time>
    </timestamp>
    <lps331>
      <t>24,5</t>
      <p>1011</p>
    </lps331>
    <hdc1080>
      <t>25,7724</t>
      <hum>33</hum>
    </hdc1080>
  </report>
  <report id="73">
    <timestamp>
      <date>2019.02.24</date>
      <time>21:56:33.984</time>
    </timestamp>
    <lps331>
      <t>24,5</t>
      <p>1011</p>
    </lps331>
    <hdc1080>
      <t>25,7724</t>
      <hum>34</hum>
    </hdc1080>
  </report>
  <report id="74">
    <timestamp>
      <date>2019.02.24</date>
      <time>21:56:35.074</time>
    </timestamp>
    <lps331>
      <t>24,5</t>
      <p>1011</p>
    </lps331>
    <hdc1080>
      <t>25,79254</t>
      <hum>34</hum>
    </hdc1080>
  </report>
  <report id="75">
    <timestamp>
      <date>2019.02.24</date>
      <time>21:56:35.664</time>
    </timestamp>
    <lps331>
      <t>24,5</t>
      <p>1011</p>
    </lps331>
    <hdc1080>
      <t>25,7724</t>
      <hum>34</hum>
    </hdc1080>
  </report>
  <report id="76">
    <timestamp>
      <date>2019.02.24</date>
      <time>21:56:36.757</time>
    </timestamp>
    <lps331>
      <t>24,5</t>
      <p>1011</p>
    </lps331>
    <hdc1080>
      <t>25,7724</t>
      <hum>34</hum>
    </hdc1080>
  </report>
  <report id="77">
    <timestamp>
      <date>2019.02.24</date>
      <time>21:56:37.851</time>
    </timestamp>
    <lps331>
      <t>24,5</t>
      <p>1011</p>
    </lps331>
    <hdc1080>
      <t>25,76233</t>
      <hum>34</hum>
    </hdc1080>
  </report>
  <report id="78">
    <timestamp>
      <date>2019.02.24</date>
      <time>21:56:38.941</time>
    </timestamp>
    <lps331>
      <t>24,5</t>
      <p>1011</p>
    </lps331>
    <hdc1080>
      <t>25,79254</t>
      <hum>34</hum>
    </hdc1080>
  </report>
  <report id="79">
    <timestamp>
      <date>2019.02.24</date>
      <time>21:56:40.035</time>
    </timestamp>
    <lps331>
      <t>24,5</t>
      <p>1011</p>
    </lps331>
    <hdc1080>
      <t>25,79254</t>
      <hum>34</hum>
    </hdc1080>
  </report>
  <report id="80">
    <timestamp>
      <date>2019.02.24</date>
      <time>21:56:40.625</time>
    </timestamp>
    <lps331>
      <t>24,5</t>
      <p>1011</p>
    </lps331>
    <hdc1080>
      <t>25,79254</t>
      <hum>34</hum>
    </hdc1080>
  </report>
  <report id="81">
    <timestamp>
      <date>2019.02.24</date>
      <time>21:56:41.718</time>
    </timestamp>
    <lps331>
      <t>24,5</t>
      <p>1011</p>
    </lps331>
    <hdc1080>
      <t>25,7724</t>
      <hum>34</hum>
    </hdc1080>
  </report>
  <report id="82">
    <timestamp>
      <date>2019.02.24</date>
      <time>21:56:42.808</time>
    </timestamp>
    <lps331>
      <t>24,5</t>
      <p>1011</p>
    </lps331>
    <hdc1080>
      <t>25,7724</t>
      <hum>34</hum>
    </hdc1080>
  </report>
  <report id="83">
    <timestamp>
      <date>2019.02.24</date>
      <time>21:56:43.902</time>
    </timestamp>
    <lps331>
      <t>24,5</t>
      <p>1011</p>
    </lps331>
    <hdc1080>
      <t>25,79254</t>
      <hum>34</hum>
    </hdc1080>
  </report>
</tph_report>